amuni_pysample-4.0.1.dist-info/.ipynb_checkpoints/PKG-INFO-checkpoint
amuni_pysample-4.0.1.dist-info/.ipynb_checkpoints/SOURCES-checkpoint.txt
amuni_pysample-4.0.1.dist-info/.ipynb_checkpoints/dependency_links-checkpoint.txt
amuni_pysample-4.0.1.dist-info/.ipynb_checkpoints/requires-checkpoint.txt
amuni_pysample-4.0.1.dist-info/.ipynb_checkpoints/top_level-checkpoint.txt
sample/__init__.py
sample/amuni.py
sample/main.py
amuni_pysample-4.0.1.dist-info/LICENSE
amuni_pysample-4.0.1.dist-info/METADATA
amuni_pysample-4.0.1.dist-info/WHEEL
amuni_pysample-4.0.1.dist-info/top_level.txt
amuni_pysample-4.0.1.dist-info/RECORD
