Metadata-Version: 2.1
Name: amuni-pysample
Version: 4.0.1
Summary: My sample python repo
Author-email: Amisha Muni <notdisclosed@sample.com>
License: GNU AFFERO GENERAL PUBLIC LICENSE
Project-URL: Homepage, https://github.com/amishamuni/amuni_pysample
Keywords: sample,python3
Classifier: Development Status :: 3 - Alpha
Classifier: Programming Language :: Python :: 3.11
Classifier: Operating System :: OS Independent
Classifier: License :: OSI Approved :: GNU Affero General Public License v3 or later (AGPLv3+)
Requires-Python: >=3.11
License-File: LICENSE
Requires-Dist: pytest ==7.4.2
Requires-Dist: streamlit ==1.27.1
